<?xml version='1.0' encoding='UTF-8'?>
<test theme="Местоимение"><part number="1" part_id="16"><text>Выберите правильный вариант</text><question number="1"><text>Last year my best friend, ... name is Annie, invited me to stay with her during the summer holiday</text><answers><answer isTrue="0"><text>whom</text></answer><answer isTrue="1"><text>whose</text></answer><answer isTrue="0"><text>who</text></answer></answers></question><question number="2"><text>Annie lives in Nancy, … is a beautiful town in the east of France.</text><answers><answer isTrue="1"><text>which</text></answer><answer isTrue="0"><text>where</text></answer><answer isTrue="0"><text>whose</text></answer></answers></question><question number="3"><text>She has a big apartment … overlooks the river.</text><answers><answer isTrue="0"><text>whose</text></answer><answer isTrue="1"><text>which</text></answer><answer isTrue="0"><text>who</text></answer></answers></question><question number="4"><text>The school … she works is very close to her apartment.</text><answers><answer isTrue="0"><text>why</text></answer><answer isTrue="0"><text>which</text></answer><answer isTrue="1"><text>where</text></answer></answers></question><question number="5"><text>Annie studied French at university, which is the reason … she decided to live in France.</text><answers><answer isTrue="1"><text>why</text></answer><answer isTrue="0"><text>where</text></answer><answer isTrue="0"><text>when</text></answer></answers></question><question number="6"><text>Annie teaches English to students, most of … are hoping to study in England or America and need to be able to speak English.</text><answers><answer isTrue="0"><text>which</text></answer><answer isTrue="1"><text>whom</text></answer><answer isTrue="0"><text>who</text></answer></answers></question></part><part number="2" part_id="17"><text>Выберите правильный вариант употребления указательных местоимений</text><question number="1"><text>"Can you pass me ... book, please?" "Yes, of course. Here you are."</text><answers><answer isTrue="1"><text>that</text></answer><answer isTrue="0"><text>this</text></answer><answer isTrue="0"><text>these</text></answer></answers></question><question number="2"><text>"Have you seen … film before?" "No. I hope it'll be good."</text><answers><answer isTrue="0"><text>this</text></answer><answer isTrue="1"><text>that</text></answer><answer isTrue="0"><text>those</text></answer></answers></question><question number="3"><text>"Look at … people swimming in the canal! They must be crazy!"</text><answers><answer isTrue="0"><text>that</text></answer><answer isTrue="0"><text>these</text></answer><answer isTrue="1"><text>this</text></answer></answers></question><question number="4"><text>"Could you come here and hold … wires for me, please?"</text><answers><answer isTrue="1"><text>these</text></answer><answer isTrue="0"><text>this</text></answer><answer isTrue="0"><text>those</text></answer></answers></question></part><part number="4" part_id="19"><text> Выберите правильный вариант употребления личных местоимений</text><question number="1"><text>I saw Martin this morning. … was coming out of the travel agent's.</text><answers><answer isTrue="1"><text>he</text></answer><answer isTrue="0"><text>it</text></answer><answer isTrue="0"><text>she</text></answer></answers></question><question number="2"><text>Did you ask … where he was going?</text><answers><answer isTrue="0"><text>he</text></answer><answer isTrue="1"><text>him</text></answer><answer isTrue="0"><text>his</text></answer></answers></question><question number="3"><text>He said … were going to Italy with Mary for two weeks.</text><answers><answer isTrue="0"><text>he</text></answer><answer isTrue="0"><text>them</text></answer><answer isTrue="1"><text>they</text></answer></answers></question><question number="4"><text>… both looked very excited and happy.</text><answers><answer isTrue="1"><text>they</text></answer><answer isTrue="0"><text>them</text></answer><answer isTrue="0"><text>their</text></answer></answers></question></part><part number="5" part_id="20"><text>Выберите правильный вариант</text><question number="1"><text>Have you seen … keys, Amy? I can't find them.</text><answers><answer isTrue="1"><text>my</text></answer><answer isTrue="0"><text>mine</text></answer></answers></question><question number="2"><text>I haven't seen … anywhere.</text><answers><answer isTrue="0"><text>they</text></answer><answer isTrue="1"><text>them</text></answer></answers></question><question number="3"><text>Perhaps they are in …coat pocket.</text><answers><answer isTrue="1"><text>your</text></answer><answer isTrue="0"><text>yours</text></answer></answers></question><question number="4"><text>I'll go over there and have a look for …</text><answers><answer isTrue="0"><text>theirs</text></answer><answer isTrue="1"><text>them</text></answer></answers></question><question number="5"><text>I wish you wouldn't keep biting ... nails; you're making me nervous.</text><answers><answer isTrue="1"><text>your</text></answer><answer isTrue="0"><text>my</text></answer></answers></question><question number="6"><text>I was so nervous … hands were shaking.</text><answers><answer isTrue="1"><text>my</text></answer><answer isTrue="0"><text>mine</text></answer></answers></question><question number="7"><text>Peter was seriously injured when he was hit on … head with a baseball bat.</text><answers><answer isTrue="0"><text>his</text></answer><answer isTrue="1"><text>the</text></answer></answers></question><question number="8"><text>In many European countries people kiss each other on … cheek when they meet.</text><answers><answer isTrue="1"><text>their</text></answer><answer isTrue="0"><text>theirs</text></answer></answers></question></part><part number="6" part_id="21"><text>Выберите правильный вариант употребления возвратных местоимений</text><question number="1"><text>Take care … when you go canoeing, Bob.</text><answers><answer isTrue="1"><text>yourself</text></answer><answer isTrue="0"><text>myself</text></answer></answers></question><question number="2"><text>Did you enjoy … last night, you two?</text><answers><answer isTrue="0"><text>yourself</text></answer><answer isTrue="1"><text>yourselves</text></answer></answers></question><question number="3"><text>Ben's ashamed of … for stealing your bike.</text><answers><answer isTrue="1"><text>himself</text></answer><answer isTrue="0"><text>yourself</text></answer></answers></question><question number="4"><text>I don't like Sheila. She thinks far too much of …</text><answers><answer isTrue="1"><text>herself</text></answer><answer isTrue="0"><text>yourself</text></answer></answers></question></part><part number="7" part_id="22"><text>Выберите правильный вариант</text><question number="1"><text>Billy and his penfriend wrote to … for five years before they actually met.</text><answers><answer isTrue="1"><text>each other</text></answer><answer isTrue="0"><text>themselves</text></answer></answers></question><question number="2"><text>The children were playing by … in the garden when it started snowing.</text><answers><answer isTrue="0"><text>each other</text></answer><answer isTrue="1"><text>themselves</text></answer></answers></question><question number="3"><text>Paul and Ted haven't spoken to … for days. What's wrong with them?</text><answers><answer isTrue="1"><text>each other</text></answer><answer isTrue="0"><text>themselves</text></answer></answers></question><question number="4"><text>We blame … for leaving the house unlocked.</text><answers><answer isTrue="1"><text>ourselves</text></answer><answer isTrue="0"><text>each other</text></answer></answers></question></part><part number="8" part_id="23"><text>Выберите правильный вариант</text><question number="1"><text>There's … in my room.</text><answers><answer isTrue="1"><text>someone</text></answer><answer isTrue="0"><text>anyone</text></answer></answers></question><question number="2"><text>There's … chicken in the fridge.</text><answers><answer isTrue="0"><text>any</text></answer><answer isTrue="1"><text>some</text></answer></answers></question><question number="3"><text>There's … in the freezer.</text><answers><answer isTrue="0"><text>anything</text></answer><answer isTrue="1"><text>nothing</text></answer></answers></question><question number="4"><text>Can I tell you …?</text><answers><answer isTrue="1"><text>something</text></answer><answer isTrue="0"><text>nothing</text></answer></answers></question><question number="5"><text>I've got hardly … money left.</text><answers><answer isTrue="1"><text>no</text></answer><answer isTrue="0"><text>any</text></answer></answers></question><question number="6"><text>He's given me … I asked for.</text><answers><answer isTrue="0"><text>anything</text></answer><answer isTrue="1"><text>everything</text></answer></answers></question></part><part number="9" part_id="24"><text>Выберите правильный вариант</text><question number="1"><text>Tracy and Sarah haven't seen the film. ... has seen the film...</text><answers><answer isTrue="1"><text>neither of them</text></answer><answer isTrue="0"><text>none of them</text></answer></answers></question><question number="2"><text>Lions, tigers and elephants are mammals. … are mammals.</text><answers><answer isTrue="0"><text>both of them</text></answer><answer isTrue="1"><text>all of them</text></answer></answers></question><question number="3"><text>Julie, Pam and Nick don't like rainy weather. … like rainy weather.</text><answers><answer isTrue="0"><text>neither of them</text></answer><answer isTrue="1"><text>none of them</text></answer></answers></question><question number="4"><text>Maria and Marina are good students. … are good students.</text><answers><answer isTrue="1"><text>both of them</text></answer><answer isTrue="0"><text>all of them</text></answer></answers></question></part><part number="10" part_id="25"><text>Выберите правильный вариант</text><question number="1"><text>… did you do on holiday, Julie?</text><answers><answer isTrue="1"><text>what</text></answer><answer isTrue="0"><text>which</text></answer></answers></question><question number="2"><text>I went to Egypt. Oh really? … places did you see?</text><answers><answer isTrue="0"><text>whose</text></answer><answer isTrue="1"><text>what</text></answer></answers></question><question number="3"><text>Cairo, the Pyramids, Aswan and some others. … one did you like the best?</text><answers><answer isTrue="0"><text>what</text></answer><answer isTrue="1"><text>which</text></answer></answers></question><question number="4"><text>I'm not sure. They were all fascinating. … did you think of Cairo?</text><answers><answer isTrue="1"><text>what</text></answer><answer isTrue="0"><text>which</text></answer></answers></question></part></test>